setup.py
pyimpact/__init__.py
pyimpact/cmd.py
pyimpact/server.py
pyimpact.egg-info/PKG-INFO
pyimpact.egg-info/SOURCES.txt
pyimpact.egg-info/dependency_links.txt
pyimpact.egg-info/entry_points.txt
pyimpact.egg-info/requires.txt
pyimpact.egg-info/top_level.txt