Metadata-Version: 1.0
Name: pyimpact
Version: 0.1.0
Summary: A lightweight development webserver for ImpactJS
Home-page: UNKNOWN
Author: amadeus / taddeimania
Author-email: jtaddei@gmail.com
License: UNKNOWN
Platform: UNKNOWN
